KeywordProject/find_keyword.py
KeywordProject-0.0.0.3.dist-info/METADATA
KeywordProject-0.0.0.3.dist-info/WHEEL
KeywordProject-0.0.0.3.dist-info/top_level.txt
KeywordProject-0.0.0.3.dist-info/RECORD
